argostranslate/__init__.py
argostranslate/apis.py
argostranslate/apply_bpe.py
argostranslate/argospm.py
argostranslate/cli.py
argostranslate/fewshot.py
argostranslate/models.py
argostranslate/networking.py
argostranslate/package.py
argostranslate/sbd.py
argostranslate/settings.py
argostranslate/tags.py
argostranslate/tokenizer.py
argostranslate/translate.py
argostranslate/utils.py
tests/__init__.py
tests/test_english_translations.py
tests/test_package.py
tests/test_translate.py
argostranslate-1.10.0.dist-info/LICENSE
argostranslate-1.10.0.dist-info/METADATA
argostranslate-1.10.0.dist-info/WHEEL
argostranslate-1.10.0.dist-info/entry_points.txt
argostranslate-1.10.0.dist-info/top_level.txt
argostranslate-1.10.0.dist-info/RECORD
