Metadata-Version: 2.1
Name: argostranslate
Version: 1.10.0
Summary: Open-source neural machine translation library based on OpenNMT's CTranslate2
Home-page: https://www.argosopentech.com
Author: Argos Open Technologies, LLC
Author-email: admin@argosopentech.com
License: UNKNOWN
Project-URL: Website, https://www.argosopentech.com
Project-URL: Documentation, https://argos-translate.readthedocs.io/en/latest/
Project-URL: GitHub, https://github.com/argosopentech/argos-translate
Project-URL: Forum, https://community.libretranslate.com/c/argos-translate/5
Platform: UNKNOWN
Classifier: License :: OSI Approved :: MIT License
Classifier: Programming Language :: Python :: 3
Classifier: Development Status :: 5 - Production/Stable
Requires-Python: >=3.5
License-File: LICENSE
